eblint/__init__.py
eblint/linter.py
eblint/checkers/__init__.py
eblint/checkers/base_checker.py
eblint/checkers/default_checkers.py
eblint/checkers/dependency_format_checker.py
eblint/checkers/field_order_checker.py
eblint/checkers/forbidden_field_checker.py
eblint/checkers/last_field_checker.py
eblint/checkers/mandatory_field_checker.py
eblint/checkers/violation.py
eblint-0.0.3.dist-info/licenses/LICENSE
eblint-0.0.3.dist-info/METADATA
eblint-0.0.3.dist-info/WHEEL
eblint-0.0.3.dist-info/entry_points.txt
eblint-0.0.3.dist-info/top_level.txt
eblint-0.0.3.dist-info/RECORD
