Metadata-Version: 2.4
Name: eblint
Version: 0.0.3
Summary: A linter for easybuild config files
Author-email: Leon Boschman <leon.boschman@chalmers.se>
License-Expression: GPL-2.0-or-later
Project-URL: Homepage, https://github.com/lboschman/eblint
Project-URL: Issues, https://github.com/lboschman/eblint/issues
Classifier: Programming Language :: Python :: 3
Classifier: Operating System :: OS Independent
Requires-Python: >=3.9
License-File: LICENSE
Requires-Dist: importlib-metadata; python_version < "3.10"
Dynamic: license-file
